var_processor/__init__.py
var_processor/collector/__init__.py
var_processor/collector/var_collector.py
var_processor/functional/__init__.py
var_processor/functional/on_error.py
var_processor/saver/__init__.py
var_processor/saver/var_saver.py
var_processor/utils/__init__.py
var_processor/utils/save_policy.py
var_processor-0.0.2.dist-info/LICENSE
var_processor-0.0.2.dist-info/METADATA
var_processor-0.0.2.dist-info/WHEEL
var_processor-0.0.2.dist-info/top_level.txt
var_processor-0.0.2.dist-info/RECORD
